fonduer/__init__.py
fonduer/_version.py
fonduer/meta.py
fonduer/py.typed
fonduer/candidates/__init__.py
fonduer/candidates/candidates.py
fonduer/candidates/matchers.py
fonduer/candidates/mentions.py
fonduer/candidates/models/__init__.py
fonduer/candidates/models/candidate.py
fonduer/candidates/models/caption_mention.py
fonduer/candidates/models/cell_mention.py
fonduer/candidates/models/document_mention.py
fonduer/candidates/models/figure_mention.py
fonduer/candidates/models/implicit_span_mention.py
fonduer/candidates/models/mention.py
fonduer/candidates/models/paragraph_mention.py
fonduer/candidates/models/section_mention.py
fonduer/candidates/models/span_mention.py
fonduer/candidates/models/table_mention.py
fonduer/candidates/models/temporary_context.py
fonduer/features/__init__.py
fonduer/features/feature_extractors.py
fonduer/features/featurizer.py
fonduer/features/feature_libs/__init__.py
fonduer/features/feature_libs/structural_features.py
fonduer/features/feature_libs/tabular_features.py
fonduer/features/feature_libs/textual_features.py
fonduer/features/feature_libs/tree_structs.py
fonduer/features/feature_libs/visual_features.py
fonduer/features/models/__init__.py
fonduer/features/models/feature.py
fonduer/learning/__init__.py
fonduer/learning/dataset.py
fonduer/learning/task.py
fonduer/learning/utils.py
fonduer/learning/models/__init__.py
fonduer/learning/models/marginal.py
fonduer/learning/models/prediction.py
fonduer/learning/modules/__init__.py
fonduer/learning/modules/concat_linear.py
fonduer/learning/modules/soft_cross_entropy_loss.py
fonduer/packaging/__init__.py
fonduer/packaging/fonduer_model.py
fonduer/parser/__init__.py
fonduer/parser/parser.py
fonduer/parser/lingual_parser/__init__.py
fonduer/parser/lingual_parser/lingual_parser.py
fonduer/parser/lingual_parser/simple_parser.py
fonduer/parser/lingual_parser/spacy_parser.py
fonduer/parser/models/__init__.py
fonduer/parser/models/caption.py
fonduer/parser/models/context.py
fonduer-0.9.0.dist-info/LICENSE
fonduer-0.9.0.dist-info/METADATA
fonduer-0.9.0.dist-info/WHEEL
fonduer-0.9.0.dist-info/top_level.txt
fonduer-0.9.0.dist-info/RECORD
