Metadata-Version: 2.1
Name: fonduer
Version: 0.9.0
Summary: Knowledge base construction system for richly formatted data.
Home-page: https://github.com/HazyResearch/fonduer
Author: Hazy Research
Author-email: senwu@cs.stanford.edu
License: MIT
Project-URL: Tracker, https://github.com/HazyResearch/fonduer/issues
Project-URL: Source, https://github.com/HazyResearch/fonduer
Keywords: fonduer,knowledge base construction,richly formatted data
Platform: UNKNOWN
Classifier: Development Status :: 3 - Alpha
Classifier: Intended Audience :: Developers
Classifier: Programming Language :: Python
Classifier: Programming Language :: Python :: 3
Classifier: Programming Language :: Python :: 3.6
Classifier: Programming Language :: Python :: 3.7
Classifier: Programming Language :: Python :: 3 :: Only
Requires-Python: >=3.6
License-File: LICENSE
Requires-Dist: beautifulsoup4 (>=4.8.0)
Requires-Dist: editdistance (<0.6.0,>=0.5.2)
Requires-Dist: snorkel (<0.10.0,>=0.9.5)
Requires-Dist: emmental (<0.1.0,>=0.0.6)
Requires-Dist: lxml (<5.0.0,>=4.2.5)
Requires-Dist: mlflow (<2.0.0,>=1.1.0)
Requires-Dist: numpy (<2.0,>=1.11)
Requires-Dist: pyyaml (<6.0,>=5.1)
Requires-Dist: scipy (<2.0.0,>=1.1.0)
Requires-Dist: spacy (<2.4.0,>=2.1.3)
Requires-Dist: sqlalchemy[postgresql] (<2.0.0,>=1.3.7)
Requires-Dist: torch (<2.0.0,>=1.3.1)
Requires-Dist: tqdm (<5.0.0,>=4.36.0)
Requires-Dist: treedlib (<0.2.0,>=0.1.3)
Requires-Dist: wand (<0.6.0,>=0.4.4)
Requires-Dist: ipython
Requires-Dist: deprecation
Provides-Extra: spacy_ja
Requires-Dist: fugashi[unidic-lite] (>=0.2.3) ; extra == 'spacy_ja'
Provides-Extra: spacy_zh
Requires-Dist: jieba (<0.40,>=0.39) ; extra == 'spacy_zh'
